{"teams":[{"teamId":"ferrari","teamName":"Ferrari","result":[{"grandPrix":"Australia","date":"03 Mar 2002","points":"10"},{"grandPrix":"Malaysia","date":"17 Mar 2002","points":"4"},{"grandPrix":"Brazil","date":"31 Mar 2002","points":"10"},{"grandPrix":"San Marino","date":"14 Apr 2002","points":"16"},{"grandPrix":"Spain","date":"28 Apr 2002","points":"10"},{"grandPrix":"Austria","date":"12 May 2002","points":"16"},{"grandPrix":"Monaco","date":"26 May 2002","points":"6"},{"grandPrix":"Canada","date":"09 Jun 2002","points":"14"},{"grandPrix":"Europe","date":"23 Jun 2002","points":"16"},{"grandPrix":"Great Britain","date":"07 Jul 2002","points":"16"},{"grandPrix":"France","date":"21 Jul 2002","points":"10"},{"grandPrix":"Germany","date":"28 Jul 2002","points":"13"},{"grandPrix":"Hungary","date":"18 Aug 2002","points":"16"},{"grandPrix":"Belgium","date":"01 Sep 2002","points":"16"},{"grandPrix":"Italy","date":"15 Sep 2002","points":"16"},{"grandPrix":"United States","date":"29 Sep 2002","points":"16"},{"grandPrix":"Japan","date":"13 Oct 2002","points":"16"}]},{"teamId":"minardi_asiatech","teamName":"Minardi Asiatech","result":[{"grandPrix":"Australia","date":"03 Mar 2002","points":"2"},{"grandPrix":"Malaysia","date":"17 Mar 2002","points":"0"},{"grandPrix":"Brazil","date":"31 Mar 2002","points":"0"},{"grandPrix":"San Marino","date":"14 Apr 2002","points":"0"},{"grandPrix":"Austria","date":"12 May 2002","points":"0"},{"grandPrix":"Monaco","date":"26 May 2002","points":"0"},{"grandPrix":"Canada","date":"09 Jun 2002","points":"0"},{"grandPrix":"Europe","date":"23 Jun 2002","points":"0"},{"grandPrix":"Great Britain","date":"07 Jul 2002","points":"0"},{"grandPrix":"France","date":"21 Jul 2002","points":"0"},{"grandPrix":"Germany","date":"28 Jul 2002","points":"0"},{"grandPrix":"Hungary","date":"18 Aug 2002","points":"0"},{"grandPrix":"Belgium","date":"01 Sep 2002","points":"0"},{"grandPrix":"Italy","date":"15 Sep 2002","points":"0"},{"grandPrix":"United States","date":"29 Sep 2002","points":"0"},{"grandPrix":"Japan","date":"13 Oct 2002","points":"0"}]},{"teamId":"jaguar_cosworth","teamName":"Jaguar Cosworth","result":[{"grandPrix":"Australia","date":"03 Mar 2002","points":"3"},{"grandPrix":"Malaysia","date":"17 Mar 2002","points":"0"},{"grandPrix":"Brazil","date":"31 Mar 2002","points":"0"},{"grandPrix":"San Marino","date":"14 Apr 2002","points":"0"},{"grandPrix":"Spain","date":"28 Apr 2002","points":"0"},{"grandPrix":"Austria","date":"12 May 2002","points":"0"},{"grandPrix":"Monaco","date":"26 May 2002","points":"0"},{"grandPrix":"Canada","date":"09 Jun 2002","points":"0"},{"grandPrix":"Europe","date":"23 Jun 2002","points":"0"},{"grandPrix":"Great Britain","date":"07 Jul 2002","points":"0"},{"grandPrix":"France","date":"21 Jul 2002","points":"0"},{"grandPrix":"Germany","date":"28 Jul 2002","points":"0"},{"grandPrix":"Hungary","date":"18 Aug 2002","points":"0"},{"grandPrix":"Belgium","date":"01 Sep 2002","points":"1"},{"grandPrix":"Italy","date":"15 Sep 2002","points":"4"},{"grandPrix":"United States","date":"29 Sep 2002","points":"0"},{"grandPrix":"Japan","date":"13 Oct 2002","points":"0"}]},{"teamId":"renault","teamName":"Renault","result":[{"grandPrix":"Australia","date":"03 Mar 2002","points":"0"},{"grandPrix":"Malaysia","date":"17 Mar 2002","points":"3"},{"grandPrix":"Brazil","date":"31 Mar 2002","points":"3"},{"grandPrix":"San Marino","date":"14 Apr 2002","points":"2"},{"grandPrix":"Spain","date":"28 Apr 2002","points":"0"},{"grandPrix":"Austria","date":"12 May 2002","points":"0"},{"grandPrix":"Monaco","date":"26 May 2002","points":"3"},{"grandPrix":"Canada","date":"09 Jun 2002","points":"1"},{"grandPrix":"Europe","date":"23 Jun 2002","points":"2"},{"grandPrix":"Great Britain","date":"07 Jul 2002","points":"0"},{"grandPrix":"France","date":"21 Jul 2002","points":"1"},{"grandPrix":"Germany","date":"28 Jul 2002","points":"0"},{"grandPrix":"Hungary","date":"18 Aug 2002","points":"0"},{"grandPrix":"Belgium","date":"01 Sep 2002","points":"0"},{"grandPrix":"Italy","date":"15 Sep 2002","points":"5"},{"grandPrix":"United States","date":"29 Sep 2002","points":"2"},{"grandPrix":"Japan","date":"13 Oct 2002","points":"1"}]},{"teamId":"arrows_cosworth","teamName":"Arrows Cosworth","result":[{"grandPrix":"Malaysia","date":"17 Mar 2002","points":"0"},{"grandPrix":"Brazil","date":"31 Mar 2002","points":"0"},{"grandPrix":"San Marino","date":"14 Apr 2002","points":"0"},{"grandPrix":"Spain","date":"28 Apr 2002","points":"1"},{"grandPrix":"Austria","date":"12 May 2002","points":"0"},{"grandPrix":"Monaco","date":"26 May 2002","points":"1"},{"grandPrix":"Canada","date":"09 Jun 2002","points":"0"},{"grandPrix":"Europe","date":"23 Jun 2002","points":"0"},{"grandPrix":"Great Britain","date":"07 Jul 2002","points":"0"},{"grandPrix":"Germany","date":"28 Jul 2002","points":"0"}]},{"teamId":"williams_bmw","teamName":"Williams BMW","result":[{"grandPrix":"Australia","date":"03 Mar 2002","points":"6"},{"grandPrix":"Malaysia","date":"17 Mar 2002","points":"16"},{"grandPrix":"Brazil","date":"31 Mar 2002","points":"8"},{"grandPrix":"San Marino","date":"14 Apr 2002","points":"7"},{"grandPrix":"Spain","date":"28 Apr 2002","points":"6"},{"grandPrix":"Austria","date":"12 May 2002","points":"7"},{"grandPrix":"Monaco","date":"26 May 2002","points":"4"},{"grandPrix":"Canada","date":"09 Jun 2002","points":"0"},{"grandPrix":"Europe","date":"23 Jun 2002","points":"3"},{"grandPrix":"Great Britain","date":"07 Jul 2002","points":"4"},{"grandPrix":"France","date":"21 Jul 2002","points":"5"},{"grandPrix":"Germany","date":"28 Jul 2002","points":"10"},{"grandPrix":"Hungary","date":"18 Aug 2002","points":"4"},{"grandPrix":"Belgium","date":"01 Sep 2002","points":"6"},{"grandPrix":"Italy","date":"15 Sep 2002","points":"0"},{"grandPrix":"United States","date":"29 Sep 2002","points":"3"},{"grandPrix":"Japan","date":"13 Oct 2002","points":"3"}]},{"teamId":"jordan_honda","teamName":"Jordan Honda","result":[{"grandPrix":"Australia","date":"03 Mar 2002","points":"0"},{"grandPrix":"Malaysia","date":"17 Mar 2002","points":"0"},{"grandPrix":"Brazil","date":"31 Mar 2002","points":"0"},{"grandPrix":"San Marino","date":"14 Apr 2002","points":"0"},{"grandPrix":"Spain","date":"28 Apr 2002","points":"0"},{"grandPrix":"Austria","date":"12 May 2002","points":"2"},{"grandPrix":"Monaco","date":"26 May 2002","points":"2"},{"grandPrix":"Canada","date":"09 Jun 2002","points":"2"},{"grandPrix":"Europe","date":"23 Jun 2002","points":"0"},{"grandPrix":"Great Britain","date":"07 Jul 2002","points":"0"},{"grandPrix":"France","date":"21 Jul 2002","points":"0"},{"grandPrix":"Germany","date":"28 Jul 2002","points":"0"},{"grandPrix":"Hungary","date":"18 Aug 2002","points":"1"},{"grandPrix":"Belgium","date":"01 Sep 2002","points":"0"},{"grandPrix":"Italy","date":"15 Sep 2002","points":"0"},{"grandPrix":"United States","date":"29 Sep 2002","points":"0"},{"grandPrix":"Japan","date":"13 Oct 2002","points":"2"}]},{"teamId":"sauber_petronas","teamName":"Sauber Petronas","result":[{"grandPrix":"Australia","date":"03 Mar 2002","points":"0"},{"grandPrix":"Malaysia","date":"17 Mar 2002","points":"3"},{"grandPrix":"Brazil","date":"31 Mar 2002","points":"0"},{"grandPrix":"San Marino","date":"14 Apr 2002","points":"0"},{"grandPrix":"Spain","date":"28 Apr 2002","points":"5"},{"grandPrix":"Austria","date":"12 May 2002","points":"0"},{"grandPrix":"Monaco","date":"26 May 2002","points":"0"},{"grandPrix":"Canada","date":"09 Jun 2002","points":"0"},{"grandPrix":"Europe","date":"23 Jun 2002","points":"1"},{"grandPrix":"Great Britain","date":"07 Jul 2002","points":"1"},{"grandPrix":"France","date":"21 Jul 2002","points":"0"},{"grandPrix":"Germany","date":"28 Jul 2002","points":"1"},{"grandPrix":"Hungary","date":"18 Aug 2002","points":"0"},{"grandPrix":"Belgium","date":"01 Sep 2002","points":"0"},{"grandPrix":"Italy","date":"15 Sep 2002","points":"0"},{"grandPrix":"United States","date":"29 Sep 2002","points":"0"},{"grandPrix":"Japan","date":"13 Oct 2002","points":"0"}]},{"teamId":"mclaren_mercedes","teamName":"McLaren Mercedes","result":[{"grandPrix":"Australia","date":"03 Mar 2002","points":"4"},{"grandPrix":"Malaysia","date":"17 Mar 2002","points":"0"},{"grandPrix":"Brazil","date":"31 Mar 2002","points":"4"},{"grandPrix":"San Marino","date":"14 Apr 2002","points":"1"},{"grandPrix":"Spain","date":"28 Apr 2002","points":"4"},{"grandPrix":"Austria","date":"12 May 2002","points":"1"},{"grandPrix":"Monaco","date":"26 May 2002","points":"10"},{"grandPrix":"Canada","date":"09 Jun 2002","points":"9"},{"grandPrix":"Europe","date":"23 Jun 2002","points":"4"},{"grandPrix":"Great Britain","date":"07 Jul 2002","points":"0"},{"grandPrix":"France","date":"21 Jul 2002","points":"10"},{"grandPrix":"Germany","date":"28 Jul 2002","points":"2"},{"grandPrix":"Hungary","date":"18 Aug 2002","points":"5"},{"grandPrix":"Belgium","date":"01 Sep 2002","points":"3"},{"grandPrix":"Italy","date":"15 Sep 2002","points":"0"},{"grandPrix":"United States","date":"29 Sep 2002","points":"4"},{"grandPrix":"Japan","date":"13 Oct 2002","points":"4"}]},{"teamId":"bar_honda","teamName":"BAR Honda","result":[{"grandPrix":"Australia","date":"03 Mar 2002","points":"0"},{"grandPrix":"Malaysia","date":"17 Mar 2002","points":"0"},{"grandPrix":"Brazil","date":"31 Mar 2002","points":"0"},{"grandPrix":"San Marino","date":"14 Apr 2002","points":"0"},{"grandPrix":"Spain","date":"28 Apr 2002","points":"0"},{"grandPrix":"Austria","date":"12 May 2002","points":"0"},{"grandPrix":"Monaco","date":"26 May 2002","points":"0"},{"grandPrix":"Canada","date":"09 Jun 2002","points":"0"},{"grandPrix":"Europe","date":"23 Jun 2002","points":"0"},{"grandPrix":"Great Britain","date":"07 Jul 2002","points":"5"},{"grandPrix":"France","date":"21 Jul 2002","points":"0"},{"grandPrix":"Germany","date":"28 Jul 2002","points":"0"},{"grandPrix":"Hungary","date":"18 Aug 2002","points":"0"},{"grandPrix":"Belgium","date":"01 Sep 2002","points":"0"},{"grandPrix":"Italy","date":"15 Sep 2002","points":"1"},{"grandPrix":"United States","date":"29 Sep 2002","points":"1"},{"grandPrix":"Japan","date":"13 Oct 2002","points":"0"}]},{"teamId":"toyota","teamName":"Toyota","result":[{"grandPrix":"Australia","date":"03 Mar 2002","points":"1"},{"grandPrix":"Malaysia","date":"17 Mar 2002","points":"0"},{"grandPrix":"Brazil","date":"31 Mar 2002","points":"1"},{"grandPrix":"San Marino","date":"14 Apr 2002","points":"0"},{"grandPrix":"Spain","date":"28 Apr 2002","points":"0"},{"grandPrix":"Austria","date":"12 May 2002","points":"0"},{"grandPrix":"Monaco","date":"26 May 2002","points":"0"},{"grandPrix":"Canada","date":"09 Jun 2002","points":"0"},{"grandPrix":"Europe","date":"23 Jun 2002","points":"0"},{"grandPrix":"Great Britain","date":"07 Jul 2002","points":"0"},{"grandPrix":"France","date":"21 Jul 2002","points":"0"},{"grandPrix":"Germany","date":"28 Jul 2002","points":"0"},{"grandPrix":"Hungary","date":"18 Aug 2002","points":"0"},{"grandPrix":"Belgium","date":"01 Sep 2002","points":"0"},{"grandPrix":"Italy","date":"15 Sep 2002","points":"0"},{"grandPrix":"United States","date":"29 Sep 2002","points":"0"},{"grandPrix":"Japan","date":"13 Oct 2002","points":"0"}]}],"allTeamsResult":[{"position":"1","team":"Ferrari","points":"221"},{"position":"2","team":"Williams BMW","points":"92"},{"position":"3","team":"McLaren Mercedes","points":"65"},{"position":"4","team":"Renault","points":"23"},{"position":"5","team":"Sauber Petronas","points":"11"},{"position":"6","team":"Jordan Honda","points":"9"},{"position":"7","team":"Jaguar Cosworth","points":"8"},{"position":"8","team":"BAR Honda","points":"7"},{"position":"9","team":"Minardi Asiatech","points":"2"},{"position":"10","team":"Toyota","points":"2"},{"position":"11","team":"Arrows Cosworth","points":"2"}]}