{"races":[{"raceId":"446/great-britain","grandPrix":"Great Britain","result":[{"position":"1","number":"8","racerFirstName":"Niki","racerLastName":"Lauda","racerShortName":"LAU","car":"McLaren Ford","laps":"76","time":"1:35:33.812","points":"9"},{"position":"2","number":"28","racerFirstName":"Didier","racerLastName":"Pironi","racerShortName":"PIR","car":"Ferrari","laps":"76","time":"+25.730s","points":"6"},{"position":"3","number":"27","racerFirstName":"Patrick","racerLastName":"Tambay","racerShortName":"TAM","car":"Ferrari","laps":"76","time":"+38.440s","points":"4"},{"position":"4","number":"11","racerFirstName":"Elio","racerLastName":"de Angelis","racerShortName":"DEA","car":"Lotus Ford","laps":"76","time":"+41.240s","points":"3"},{"position":"5","number":"5","racerFirstName":"Derek","racerLastName":"Daly","racerShortName":"DAL","car":"Williams Ford","laps":"76","time":"+41.430s","points":"2"},{"position":"6","number":"15","racerFirstName":"Alain","racerLastName":"Prost","racerShortName":"PRO","car":"Renault","laps":"76","time":"+41.640s","points":"1"},{"position":"7","number":"23","racerFirstName":"Bruno","racerLastName":"Giacomelli","racerShortName":"GIA","car":"Alfa Romeo","laps":"75","time":"+1 lap","points":"0"},{"position":"8","number":"4","racerFirstName":"Brian","racerLastName":"Henton","racerShortName":"HEN","car":"Tyrrell Ford","laps":"75","time":"+1 lap","points":"0"},{"position":"9","number":"30","racerFirstName":"Mauro","racerLastName":"Baldi","racerShortName":"BAL","car":"Arrows Ford","laps":"74","time":"+2 laps","points":"0"},{"position":"10","number":"17","racerFirstName":"Jochen","racerLastName":"Mass","racerShortName":"MAS","car":"March Ford","laps":"73","time":"+3 laps","points":"0"},{"position":"NC","number":"22","racerFirstName":"Andrea","racerLastName":"de Cesaris","racerShortName":"DEC","car":"Alfa Romeo","laps":"66","time":"DNF","points":"0"},{"position":"NC","number":"25","racerFirstName":"Eddie","racerLastName":"Cheever","racerShortName":"CHE","car":"Ligier Matra","laps":"60","time":"DNF","points":"0"},{"position":"NC","number":"29","racerFirstName":"Marc","racerLastName":"Surer","racerShortName":"SUR","car":"Arrows Ford","laps":"59","time":"DNF","points":"0"},{"position":"NC","number":"6","racerFirstName":"Keke","racerLastName":"Rosberg","racerShortName":"ROS","car":"Williams Ford","laps":"50","time":"DNF","points":"0"},{"position":"NC","number":"3","racerFirstName":"Michele","racerLastName":"Alboreto","racerShortName":"ALB","car":"Tyrrell Ford","laps":"44","time":"DNC","points":"0"},{"position":"NC","number":"26","racerFirstName":"Jacques","racerLastName":"Laffite","racerShortName":"LAF","car":"Ligier Matra","laps":"41","time":"DNF","points":"0"},{"position":"NC","number":"35","racerFirstName":"Derek","racerLastName":"Warwick","racerShortName":"WAR","car":"Toleman Hart","laps":"40","time":"DNF","points":"0"},{"position":"NC","number":"12","racerFirstName":"Nigel","racerLastName":"Mansell","racerShortName":"MAN","car":"Lotus Ford","laps":"29","time":"DNF","points":"0"},{"position":"NC","number":"1","racerFirstName":"Nelson","racerLastName":"Piquet","racerShortName":"PIQ","car":"Brabham BMW","laps":"9","time":"DNF","points":"0"},{"position":"NC","number":"14","racerFirstName":"Roberto","racerLastName":"Guerrero","racerShortName":"GUE","car":"Ensign Ford","laps":"3","time":"DNF","points":"0"},{"position":"NC","number":"31","racerFirstName":"Jean-Pierre","racerLastName":"Jarier","racerShortName":"JAR","car":"Osella Ford","laps":"2","time":"DNF","points":"0"},{"position":"NC","number":"20","racerFirstName":"Chico","racerLastName":"Serra","racerShortName":"SER","car":"Fittipaldi Ford","laps":"2","time":"DNF","points":"0"},{"position":"NC","number":"7","racerFirstName":"John","racerLastName":"Watson","racerShortName":"WAT","car":"McLaren Ford","laps":"2","time":"DNF","points":"0"},{"position":"NC","number":"36","racerFirstName":"Teo","racerLastName":"Fabi","racerShortName":"FAB","car":"Toleman Hart","laps":"0","time":"DNF","points":"0"},{"position":"NC","number":"16","racerFirstName":"Rene","racerLastName":"Arnoux","racerShortName":"ARN","car":"Renault","laps":"0","time":"DNF","points":"0"},{"position":"NC","number":"2","racerFirstName":"Riccardo","racerLastName":"Patrese","racerShortName":"PAT","car":"Brabham BMW","laps":"0","time":"DNF","points":"0"}]},{"raceId":"442/monaco","grandPrix":"Monaco","result":[{"position":"1","number":"2","racerFirstName":"Riccardo","racerLastName":"Patrese","racerShortName":"PAT","car":"Brabham Ford","laps":"76","time":"1:54:11.259","points":"9"},{"position":"2","number":"28","racerFirstName":"Didier","racerLastName":"Pironi","racerShortName":"PIR","car":"Ferrari","laps":"75","time":"DNF","points":"6"},{"position":"3","number":"22","racerFirstName":"Andrea","racerLastName":"de Cesaris","racerShortName":"DEC","car":"Alfa Romeo","laps":"75","time":"DNF","points":"4"},{"position":"4","number":"12","racerFirstName":"Nigel","racerLastName":"Mansell","racerShortName":"MAN","car":"Lotus Ford","laps":"75","time":"+1 lap","points":"3"},{"position":"5","number":"11","racerFirstName":"Elio","racerLastName":"de Angelis","racerShortName":"DEA","car":"Lotus Ford","laps":"75","time":"+1 lap","points":"2"},{"position":"6","number":"5","racerFirstName":"Derek","racerLastName":"Daly","racerShortName":"DAL","car":"Williams Ford","laps":"74","time":"DNF","points":"1"},{"position":"7","number":"15","racerFirstName":"Alain","racerLastName":"Prost","racerShortName":"PRO","car":"Renault","laps":"73","time":"DNF","points":"0"},{"position":"8","number":"4","racerFirstName":"Brian","racerLastName":"Henton","racerShortName":"HEN","car":"Tyrrell Ford","laps":"72","time":"+4 laps","points":"0"},{"position":"9","number":"29","racerFirstName":"Marc","racerLastName":"Surer","racerShortName":"SUR","car":"Arrows Ford","laps":"70","time":"+6 laps","points":"0"},{"position":"10","number":"3","racerFirstName":"Michele","racerLastName":"Alboreto","racerShortName":"ALB","car":"Tyrrell Ford","laps":"69","time":"DNF","points":"0"},{"position":"NC","number":"6","racerFirstName":"Keke","racerLastName":"Rosberg","racerShortName":"ROS","car":"Williams Ford","laps":"64","time":"DNF","points":"0"},{"position":"NC","number":"8","racerFirstName":"Niki","racerLastName":"Lauda","racerShortName":"LAU","car":"McLaren Ford","laps":"56","time":"DNF","points":"0"},{"position":"NC","number":"1","racerFirstName":"Nelson","racerLastName":"Piquet","racerShortName":"PIQ","car":"Brabham BMW","laps":"49","time":"DNF","points":"0"},{"position":"NC","number":"7","racerFirstName":"John","racerLastName":"Watson","racerShortName":"WAT","car":"McLaren Ford","laps":"35","time":"DNF","points":"0"},{"position":"NC","number":"9","racerFirstName":"Manfred","racerLastName":"Winkelhock","racerShortName":"WIN","car":"ATS Ford","laps":"31","time":"DNF","points":"0"},{"position":"NC","number":"26","racerFirstName":"Jacques","racerLastName":"Laffite","racerShortName":"LAF","car":"Ligier Matra","laps":"29","time":"DNF","points":"0"},{"position":"NC","number":"25","racerFirstName":"Eddie","racerLastName":"Cheever","racerShortName":"CHE","car":"Ligier Matra","laps":"27","time":"DNF","points":"0"},{"position":"NC","number":"10","racerFirstName":"Eliseo","racerLastName":"Salazar","racerShortName":"SAL","car":"ATS Ford","laps":"22","time":"DNF","points":"0"},{"position":"NC","number":"16","racerFirstName":"Rene","racerLastName":"Arnoux","racerShortName":"ARN","car":"Renault","laps":"14","time":"DNF","points":"0"},{"position":"NC","number":"23","racerFirstName":"Bruno","racerLastName":"Giacomelli","racerShortName":"GIA","car":"Alfa Romeo","laps":"4","time":"DNF","points":"0"}]},{"raceId":"439/usa-west","grandPrix":"United States","result":[{"position":"1","number":"8","racerFirstName":"Niki","racerLastName":"Lauda","racerShortName":"LAU","car":"McLaren Ford","laps":"75","time":"1:58:25.318","points":"9"},{"position":"2","number":"6","racerFirstName":"Keke","racerLastName":"Rosberg","racerShortName":"ROS","car":"Williams Ford","laps":"75","time":"+14.660s","points":"6"},{"position":"DQ","number":"27","racerFirstName":"Gilles","racerLastName":"Villeneuve","racerShortName":"VIL","car":"Ferrari","laps":"75","time":"DSQ","points":"0"},{"position":"3","number":"2","racerFirstName":"Riccardo","racerLastName":"Patrese","racerShortName":"PAT","car":"Brabham Ford","laps":"75","time":"+79.140s","points":"4"},{"position":"4","number":"3","racerFirstName":"Michele","racerLastName":"Alboreto","racerShortName":"ALB","car":"Tyrrell Ford","laps":"75","time":"+80.950s","points":"3"},{"position":"5","number":"11","racerFirstName":"Elio","racerLastName":"de Angelis","racerShortName":"DEA","car":"Lotus Ford","laps":"74","time":"+1 lap","points":"2"},{"position":"6","number":"7","racerFirstName":"John","racerLastName":"Watson","racerShortName":"WAT","car":"McLaren Ford","laps":"74","time":"+1 lap","points":"1"},{"position":"7","number":"12","racerFirstName":"Nigel","racerLastName":"Mansell","racerShortName":"MAN","car":"Lotus Ford","laps":"73","time":"+2 laps","points":"0"},{"position":"8","number":"17","racerFirstName":"Jochen","racerLastName":"Mass","racerShortName":"MAS","car":"March Ford","laps":"73","time":"+2 laps","points":"0"},{"position":"9","number":"18","racerFirstName":"Raul","racerLastName":"Boesel","racerShortName":"BOE","car":"March Ford","laps":"70","time":"+5 laps","points":"0"},{"position":"10","number":"4","racerFirstName":"Slim","racerLastName":"Borgudd","racerShortName":"BOR","car":"Tyrrell Ford","laps":"68","time":"+7 laps","points":"0"},{"position":"NC","number":"25","racerFirstName":"Eddie","racerLastName":"Cheever","racerShortName":"CHE","car":"Ligier Matra","laps":"59","time":"DNF","points":"0"},{"position":"NC","number":"22","racerFirstName":"Andrea","racerLastName":"de Cesaris","racerShortName":"DEC","car":"Alfa Romeo","laps":"33","time":"DNF","points":"0"},{"position":"NC","number":"29","racerFirstName":"Brian","racerLastName":"Henton","racerShortName":"HEN","car":"Arrows Ford","laps":"32","time":"DNF","points":"0"},{"position":"NC","number":"14","racerFirstName":"Roberto","racerLastName":"Guerrero","racerShortName":"GUE","car":"Ensign Ford","laps":"27","time":"DNF","points":"0"},{"position":"NC","number":"26","racerFirstName":"Jacques","racerLastName":"Laffite","racerShortName":"LAF","car":"Ligier Matra","laps":"26","time":"DNF","points":"0"},{"position":"NC","number":"31","racerFirstName":"Jean-Pierre","racerLastName":"Jarier","racerShortName":"JAR","car":"Osella Ford","laps":"26","time":"DNF","points":"0"},{"position":"NC","number":"1","racerFirstName":"Nelson","racerLastName":"Piquet","racerShortName":"PIQ","car":"Brabham Ford","laps":"25","time":"DNF","points":"0"},{"position":"NC","number":"33","racerFirstName":"Derek","racerLastName":"Daly","racerShortName":"DAL","car":"Theodore Ford","laps":"23","time":"DNF","points":"0"},{"position":"NC","number":"5","racerFirstName":"Mario","racerLastName":"Andretti","racerShortName":"AND","car":"Williams Ford","laps":"19","time":"DNF","points":"0"},{"position":"NC","number":"15","racerFirstName":"Alain","racerLastName":"Prost","racerShortName":"PRO","car":"Renault","laps":"10","time":"DNF","points":"0"},{"position":"NC","number":"28","racerFirstName":"Didier","racerLastName":"Pironi","racerShortName":"PIR","car":"Ferrari","laps":"6","time":"DNF","points":"0"},{"position":"NC","number":"16","racerFirstName":"Rene","racerLastName":"Arnoux","racerShortName":"ARN","car":"Renault","laps":"5","time":"DNF","points":"0"},{"position":"NC","number":"23","racerFirstName":"Bruno","racerLastName":"Giacomelli","racerShortName":"GIA","car":"Alfa Romeo","laps":"5","time":"DNF","points":"0"},{"position":"NC","number":"10","racerFirstName":"Eliseo","racerLastName":"Salazar","racerShortName":"SAL","car":"ATS Ford","laps":"3","time":"DNF","points":"0"},{"position":"NC","number":"9","racerFirstName":"Manfred","racerLastName":"Winkelhock","racerShortName":"WIN","car":"ATS Ford","laps":"1","time":"DNF","points":"0"}]},{"raceId":"452/las-vegas","grandPrix":"United States","result":[{"position":"1","number":"3","racerFirstName":"Michele","racerLastName":"Alboreto","racerShortName":"ALB","car":"Tyrrell Ford","laps":"75","time":"1:41:56.888","points":"9"},{"position":"2","number":"7","racerFirstName":"John","racerLastName":"Watson","racerShortName":"WAT","car":"McLaren Ford","laps":"75","time":"+27.290s","points":"6"},{"position":"3","number":"25","racerFirstName":"Eddie","racerLastName":"Cheever","racerShortName":"CHE","car":"Ligier Matra","laps":"75","time":"+56.450s","points":"4"},{"position":"4","number":"15","racerFirstName":"Alain","racerLastName":"Prost","racerShortName":"PRO","car":"Renault","laps":"75","time":"+68.650s","points":"3"},{"position":"5","number":"6","racerFirstName":"Keke","racerLastName":"Rosberg","racerShortName":"ROS","car":"Williams Ford","laps":"75","time":"+71.380s","points":"2"},{"position":"6","number":"5","racerFirstName":"Derek","racerLastName":"Daly","racerShortName":"DAL","car":"Williams Ford","laps":"74","time":"+1 lap","points":"1"},{"position":"7","number":"29","racerFirstName":"Marc","racerLastName":"Surer","racerShortName":"SUR","car":"Arrows Ford","laps":"74","time":"+1 lap","points":"0"},{"position":"8","number":"4","racerFirstName":"Brian","racerLastName":"Henton","racerShortName":"HEN","car":"Tyrrell Ford","laps":"74","time":"+1 lap","points":"0"},{"position":"9","number":"22","racerFirstName":"Andrea","racerLastName":"de Cesaris","racerShortName":"DEC","car":"Alfa Romeo","laps":"73","time":"+2 laps","points":"0"},{"position":"10","number":"23","racerFirstName":"Bruno","racerLastName":"Giacomelli","racerShortName":"GIA","car":"Alfa Romeo","laps":"73","time":"+2 laps","points":"0"},{"position":"11","number":"30","racerFirstName":"Mauro","racerLastName":"Baldi","racerShortName":"BAL","car":"Arrows Ford","laps":"73","time":"+2 laps","points":"0"},{"position":"12","number":"17","racerFirstName":"Rupert","racerLastName":"Keegan","racerShortName":"KEE","car":"March Ford","laps":"73","time":"+2 laps","points":"0"},{"position":"13","number":"18","racerFirstName":"Raul","racerLastName":"Boesel","racerShortName":"BOE","car":"March Ford","laps":"69","time":"+6 laps","points":"0"},{"position":"NC","number":"9","racerFirstName":"Manfred","racerLastName":"Winkelhock","racerShortName":"WIN","car":"ATS Ford","laps":"62","time":"DNC","points":"0"},{"position":"NC","number":"8","racerFirstName":"Niki","racerLastName":"Lauda","racerShortName":"LAU","car":"McLaren Ford","laps":"53","time":"DNF","points":"0"},{"position":"NC","number":"33","racerFirstName":"Tommy","racerLastName":"Byrne","racerShortName":"BYR","car":"Theodore Ford","laps":"39","time":"DNF","points":"0"},{"position":"NC","number":"35","racerFirstName":"Derek","racerLastName":"Warwick","racerShortName":"WAR","car":"Toleman Hart","laps":"32","time":"DNF","points":"0"},{"position":"NC","number":"11","racerFirstName":"Elio","racerLastName":"de Angelis","racerShortName":"DEA","car":"Lotus Ford","laps":"28","time":"DNF","points":"0"},{"position":"NC","number":"28","racerFirstName":"Mario","racerLastName":"Andretti","racerShortName":"AND","car":"Ferrari","laps":"26","time":"DNF","points":"0"},{"position":"NC","number":"1","racerFirstName":"Nelson","racerLastName":"Piquet","racerShortName":"PIQ","car":"Brabham BMW","laps":"26","time":"DNF","points":"0"},{"position":"NC","number":"16","racerFirstName":"Rene","racerLastName":"Arnoux","racerShortName":"ARN","car":"Renault","laps":"20","time":"DNF","points":"0"},{"position":"NC","number":"2","racerFirstName":"Riccardo","racerLastName":"Patrese","racerShortName":"PAT","car":"Brabham BMW","laps":"17","time":"DNF","points":"0"},{"position":"NC","number":"12","racerFirstName":"Nigel","racerLastName":"Mansell","racerShortName":"MAN","car":"Lotus Ford","laps":"8","time":"DNF","points":"0"},{"position":"NC","number":"26","racerFirstName":"Jacques","racerLastName":"Laffite","racerShortName":"LAF","car":"Ligier Matra","laps":"5","time":"DNF","points":"0"}]},{"raceId":"440/san-marino","grandPrix":"San Marino","result":[{"position":"1","number":"28","racerFirstName":"Didier","racerLastName":"Pironi","racerShortName":"PIR","car":"Ferrari","laps":"60","time":"1:36:38.887","points":"9"},{"position":"2","number":"27","racerFirstName":"Gilles","racerLastName":"Villeneuve","racerShortName":"VIL","car":"Ferrari","laps":"60","time":"+0.370s","points":"6"},{"position":"3","number":"3","racerFirstName":"Michele","racerLastName":"Alboreto","racerShortName":"ALB","car":"Tyrrell Ford","laps":"60","time":"+67.680s","points":"4"},{"position":"4","number":"31","racerFirstName":"Jean-Pierre","racerLastName":"Jarier","racerShortName":"JAR","car":"Osella Ford","laps":"59","time":"+1 lap","points":"3"},{"position":"5","number":"10","racerFirstName":"Eliseo","racerLastName":"Salazar","racerShortName":"SAL","car":"ATS Ford","laps":"57","time":"+3 laps","points":"2"},{"position":"DQ","number":"9","racerFirstName":"Manfred","racerLastName":"Winkelhock","racerShortName":"WIN","car":"ATS Ford","laps":"54","time":"DSQ","points":"0"},{"position":"NC","number":"36","racerFirstName":"Teo","racerLastName":"Fabi","racerShortName":"FAB","car":"Toleman Hart","laps":"52","time":"+8 laps","points":"0"},{"position":"NC","number":"16","racerFirstName":"Rene","racerLastName":"Arnoux","racerShortName":"ARN","car":"Renault","laps":"44","time":"DNF","points":"0"},{"position":"NC","number":"23","racerFirstName":"Bruno","racerLastName":"Giacomelli","racerShortName":"GIA","car":"Alfa Romeo","laps":"24","time":"DNF","points":"0"},{"position":"NC","number":"32","racerFirstName":"Riccardo","racerLastName":"Paletti","racerShortName":"PAL","car":"Osella Ford","laps":"7","time":"DNF","points":"0"},{"position":"NC","number":"15","racerFirstName":"Alain","racerLastName":"Prost","racerShortName":"PRO","car":"Renault","laps":"6","time":"DNF","points":"0"},{"position":"NC","number":"22","racerFirstName":"Andrea","racerLastName":"de Cesaris","racerShortName":"DEC","car":"Alfa Romeo","laps":"4","time":"DNF","points":"0"},{"position":"NC","number":"4","racerFirstName":"Brian","racerLastName":"Henton","racerShortName":"HEN","car":"Tyrrell Ford","laps":"0","time":"DNF","points":"0"}]},{"raceId":"443/detroit","grandPrix":"Detroit","result":[{"position":"1","number":"7","racerFirstName":"John","racerLastName":"Watson","racerShortName":"WAT","car":"McLaren Ford","laps":"62","time":"1:58:41.043","points":"9"},{"position":"2","number":"25","racerFirstName":"Eddie","racerLastName":"Cheever","racerShortName":"CHE","car":"Ligier Matra","laps":"62","time":"+15.730s","points":"6"},{"position":"3","number":"28","racerFirstName":"Didier","racerLastName":"Pironi","racerShortName":"PIR","car":"Ferrari","laps":"62","time":"+28.080s","points":"4"},{"position":"4","number":"6","racerFirstName":"Keke","racerLastName":"Rosberg","racerShortName":"ROS","car":"Williams Ford","laps":"62","time":"+71.980s","points":"3"},{"position":"5","number":"5","racerFirstName":"Derek","racerLastName":"Daly","racerShortName":"DAL","car":"Williams Ford","laps":"62","time":"+83.760s","points":"2"},{"position":"6","number":"26","racerFirstName":"Jacques","racerLastName":"Laffite","racerShortName":"LAF","car":"Ligier Matra","laps":"61","time":"+1 lap","points":"1"},{"position":"7","number":"17","racerFirstName":"Jochen","racerLastName":"Mass","racerShortName":"MAS","car":"March Ford","laps":"61","time":"+1 lap","points":"0"},{"position":"8","number":"29","racerFirstName":"Marc","racerLastName":"Surer","racerShortName":"SUR","car":"Arrows Ford","laps":"61","time":"+1 lap","points":"0"},{"position":"9","number":"4","racerFirstName":"Brian","racerLastName":"Henton","racerShortName":"HEN","car":"Tyrrell Ford","laps":"60","time":"+2 laps","points":"0"},{"position":"10","number":"16","racerFirstName":"Rene","racerLastName":"Arnoux","racerShortName":"ARN","car":"Renault","laps":"59","time":"+3 laps","points":"0"},{"position":"11","number":"20","racerFirstName":"Chico","racerLastName":"Serra","racerShortName":"SER","car":"Fittipaldi Ford","laps":"59","time":"+3 laps","points":"0"},{"position":"NC","number":"15","racerFirstName":"Alain","racerLastName":"Prost","racerShortName":"PRO","car":"Renault","laps":"54","time":"+8 laps","points":"0"},{"position":"NC","number":"12","racerFirstName":"Nigel","racerLastName":"Mansell","racerShortName":"MAN","car":"Lotus Ford","laps":"44","time":"DNF","points":"0"},{"position":"NC","number":"8","racerFirstName":"Niki","racerLastName":"Lauda","racerShortName":"LAU","car":"McLaren Ford","laps":"40","time":"DNF","points":"0"},{"position":"NC","number":"3","racerFirstName":"Michele","racerLastName":"Alboreto","racerShortName":"ALB","car":"Tyrrell Ford","laps":"40","time":"DNF","points":"0"},{"position":"NC","number":"23","racerFirstName":"Bruno","racerLastName":"Giacomelli","racerShortName":"GIA","car":"Alfa Romeo","laps":"30","time":"DNF","points":"0"},{"position":"NC","number":"11","racerFirstName":"Elio","racerLastName":"de Angelis","racerShortName":"DEA","car":"Lotus Ford","laps":"17","time":"DNF","points":"0"},{"position":"NC","number":"10","racerFirstName":"Eliseo","racerLastName":"Salazar","racerShortName":"SAL","car":"ATS Ford","laps":"13","time":"DNF","points":"0"},{"position":"NC","number":"14","racerFirstName":"Roberto","racerLastName":"Guerrero","racerShortName":"GUE","car":"Ensign Ford","laps":"6","time":"DNF","points":"0"},{"position":"NC","number":"2","racerFirstName":"Riccardo","racerLastName":"Patrese","racerShortName":"PAT","car":"Brabham Ford","laps":"6","time":"DNF","points":"0"},{"position":"NC","number":"22","racerFirstName":"Andrea","racerLastName":"de Cesaris","racerShortName":"DEC","car":"Alfa Romeo","laps":"2","time":"DNF","points":"0"},{"position":"NC","number":"31","racerFirstName":"Jean-Pierre","racerLastName":"Jarier","racerShortName":"JAR","car":"Osella Ford","laps":"2","time":"DNF","points":"0"},{"position":"NC","number":"9","racerFirstName":"Manfred","racerLastName":"Winkelhock","racerShortName":"WIN","car":"ATS Ford","laps":"1","time":"DNF","points":"0"},{"position":"NC","number":"18","racerFirstName":"Raul","racerLastName":"Boesel","racerShortName":"BOE","car":"March Ford","laps":"0","time":"DNF","points":"0"},{"position":"NC","number":"30","racerFirstName":"Mauro","racerLastName":"Baldi","racerShortName":"BAL","car":"Arrows Ford","laps":"0","time":"DNF","points":"0"}]},{"raceId":"441/belgium","grandPrix":"Belgium","result":[{"position":"1","number":"7","racerFirstName":"John","racerLastName":"Watson","racerShortName":"WAT","car":"McLaren Ford","laps":"70","time":"1:35:41.995","points":"9"},{"position":"2","number":"6","racerFirstName":"Keke","racerLastName":"Rosberg","racerShortName":"ROS","car":"Williams Ford","laps":"70","time":"+7.268s","points":"6"},{"position":"DQ","number":"8","racerFirstName":"Niki","racerLastName":"Lauda","racerShortName":"LAU","car":"McLaren Ford","laps":"70","time":"DSQ","points":"0"},{"position":"3","number":"25","racerFirstName":"Eddie","racerLastName":"Cheever","racerShortName":"CHE","car":"Ligier Matra","laps":"69","time":"+1 lap","points":"4"},{"position":"4","number":"11","racerFirstName":"Elio","racerLastName":"de Angelis","racerShortName":"DEA","car":"Lotus Ford","laps":"68","time":"+2 laps","points":"3"},{"position":"5","number":"1","racerFirstName":"Nelson","racerLastName":"Piquet","racerShortName":"PIQ","car":"Brabham BMW","laps":"67","time":"+3 laps","points":"2"},{"position":"6","number":"20","racerFirstName":"Chico","racerLastName":"Serra","racerShortName":"SER","car":"Fittipaldi Ford","laps":"67","time":"+3 laps","points":"1"},{"position":"7","number":"29","racerFirstName":"Marc","racerLastName":"Surer","racerShortName":"SUR","car":"Arrows Ford","laps":"66","time":"+4 laps","points":"0"},{"position":"8","number":"18","racerFirstName":"Raul","racerLastName":"Boesel","racerShortName":"BOE","car":"March Ford","laps":"66","time":"+4 laps","points":"0"},{"position":"9","number":"26","racerFirstName":"Jacques","racerLastName":"Laffite","racerShortName":"LAF","car":"Ligier Matra","laps":"66","time":"+4 laps","points":"0"},{"position":"NC","number":"5","racerFirstName":"Derek","racerLastName":"Daly","racerShortName":"DAL","car":"Williams Ford","laps":"60","time":"DNF","points":"0"},{"position":"NC","number":"17","racerFirstName":"Jochen","racerLastName":"Mass","racerShortName":"MAS","car":"March Ford","laps":"60","time":"DNF","points":"0"},{"position":"NC","number":"15","racerFirstName":"Alain","racerLastName":"Prost","racerShortName":"PRO","car":"Renault","laps":"59","time":"DNF","points":"0"},{"position":"NC","number":"2","racerFirstName":"Riccardo","racerLastName":"Patrese","racerShortName":"PAT","car":"Brabham BMW","laps":"52","time":"DNF","points":"0"},{"position":"NC","number":"30","racerFirstName":"Mauro","racerLastName":"Baldi","racerShortName":"BAL","car":"Arrows Ford","laps":"51","time":"DNF","points":"0"},{"position":"NC","number":"31","racerFirstName":"Jean-Pierre","racerLastName":"Jarier","racerShortName":"JAR","car":"Osella Ford","laps":"37","time":"DNF","points":"0"},{"position":"NC","number":"22","racerFirstName":"Andrea","racerLastName":"de Cesaris","racerShortName":"DEC","car":"Alfa Romeo","laps":"34","time":"DNF","points":"0"},{"position":"NC","number":"4","racerFirstName":"Brian","racerLastName":"Henton","racerShortName":"HEN","car":"Tyrrell Ford","laps":"33","time":"DNF","points":"0"},{"position":"NC","number":"3","racerFirstName":"Michele","racerLastName":"Alboreto","racerShortName":"ALB","car":"Tyrrell Ford","laps":"29","time":"DNF","points":"0"},{"position":"NC","number":"35","racerFirstName":"Derek","racerLastName":"Warwick","racerShortName":"WAR","car":"Toleman Hart","laps":"29","time":"DNF","points":"0"},{"position":"NC","number":"36","racerFirstName":"Teo","racerLastName":"Fabi","racerShortName":"FAB","car":"Toleman Hart","laps":"13","time":"DNF","points":"0"},{"position":"NC","number":"12","racerFirstName":"Nigel","racerLastName":"Mansell","racerShortName":"MAN","car":"Lotus Ford","laps":"9","time":"DNF","points":"0"},{"position":"NC","number":"16","racerFirstName":"Rene","racerLastName":"Arnoux","racerShortName":"ARN","car":"Renault","laps":"7","time":"DNF","points":"0"},{"position":"NC","number":"9","racerFirstName":"Manfred","racerLastName":"Winkelhock","racerShortName":"WIN","car":"ATS Ford","laps":"0","time":"DNF","points":"0"},{"position":"NC","number":"10","racerFirstName":"Eliseo","racerLastName":"Salazar","racerShortName":"SAL","car":"ATS Ford","laps":"0","time":"DNF","points":"0"},{"position":"NC","number":"23","racerFirstName":"Bruno","racerLastName":"Giacomelli","racerShortName":"GIA","car":"Alfa Romeo","laps":"0","time":"DNF","points":"0"}]},{"raceId":"445/netherlands","grandPrix":"Netherlands","result":[{"position":"1","number":"28","racerFirstName":"Didier","racerLastName":"Pironi","racerShortName":"PIR","car":"Ferrari","laps":"72","time":"1:38:03.254","points":"9"},{"position":"2","number":"1","racerFirstName":"Nelson","racerLastName":"Piquet","racerShortName":"PIQ","car":"Brabham BMW","laps":"72","time":"+21.650s","points":"6"},{"position":"3","number":"6","racerFirstName":"Keke","racerLastName":"Rosberg","racerShortName":"ROS","car":"Williams Ford","laps":"72","time":"+22.370s","points":"4"},{"position":"4","number":"8","racerFirstName":"Niki","racerLastName":"Lauda","racerShortName":"LAU","car":"McLaren Ford","laps":"72","time":"+83.720s","points":"3"},{"position":"5","number":"5","racerFirstName":"Derek","racerLastName":"Daly","racerShortName":"DAL","car":"Williams Ford","laps":"71","time":"+1 lap","points":"2"},{"position":"6","number":"30","racerFirstName":"Mauro","racerLastName":"Baldi","racerShortName":"BAL","car":"Arrows Ford","laps":"71","time":"+1 lap","points":"1"},{"position":"7","number":"3","racerFirstName":"Michele","racerLastName":"Alboreto","racerShortName":"ALB","car":"Tyrrell Ford","laps":"71","time":"+1 lap","points":"0"},{"position":"8","number":"27","racerFirstName":"Patrick","racerLastName":"Tambay","racerShortName":"TAM","car":"Ferrari","laps":"71","time":"+1 lap","points":"0"},{"position":"9","number":"7","racerFirstName":"John","racerLastName":"Watson","racerShortName":"WAT","car":"McLaren Ford","laps":"71","time":"+1 lap","points":"0"},{"position":"10","number":"29","racerFirstName":"Marc","racerLastName":"Surer","racerShortName":"SUR","car":"Arrows Ford","laps":"71","time":"+1 lap","points":"0"},{"position":"11","number":"23","racerFirstName":"Bruno","racerLastName":"Giacomelli","racerShortName":"GIA","car":"Alfa Romeo","laps":"70","time":"+2 laps","points":"0"},{"position":"12","number":"9","racerFirstName":"Manfred","racerLastName":"Winkelhock","racerShortName":"WIN","car":"ATS Ford","laps":"70","time":"+2 laps","points":"0"},{"position":"13","number":"10","racerFirstName":"Eliseo","racerLastName":"Salazar","racerShortName":"SAL","car":"ATS Ford","laps":"70","time":"+2 laps","points":"0"},{"position":"14","number":"31","racerFirstName":"Jean-Pierre","racerLastName":"Jarier","racerShortName":"JAR","car":"Osella Ford","laps":"69","time":"+3 laps","points":"0"},{"position":"15","number":"2","racerFirstName":"Riccardo","racerLastName":"Patrese","racerShortName":"PAT","car":"Brabham BMW","laps":"69","time":"+3 laps","points":"0"},{"position":"NC","number":"17","racerFirstName":"Jochen","racerLastName":"Mass","racerShortName":"MAS","car":"March Ford","laps":"60","time":"DNF","points":"0"},{"position":"NC","number":"33","racerFirstName":"Jan","racerLastName":"Lammers","racerShortName":"LAM","car":"Theodore Ford","laps":"41","time":"DNF","points":"0"},{"position":"NC","number":"11","racerFirstName":"Elio","racerLastName":"de Angelis","racerShortName":"DEA","car":"Lotus Ford","laps":"40","time":"DNF","points":"0"},{"position":"NC","number":"22","racerFirstName":"Andrea","racerLastName":"de Cesaris","racerShortName":"DEC","car":"Alfa Romeo","laps":"35","time":"DNF","points":"0"},{"position":"NC","number":"15","racerFirstName":"Alain","racerLastName":"Prost","racerShortName":"PRO","car":"Renault","laps":"33","time":"DNF","points":"0"},{"position":"NC","number":"16","racerFirstName":"Rene","racerLastName":"Arnoux","racerShortName":"ARN","car":"Renault","laps":"21","time":"DNF","points":"0"},{"position":"NC","number":"4","racerFirstName":"Brian","racerLastName":"Henton","racerShortName":"HEN","car":"Tyrrell Ford","laps":"21","time":"DNF","points":"0"},{"position":"NC","number":"18","racerFirstName":"Raul","racerLastName":"Boesel","racerShortName":"BOE","car":"March Ford","laps":"21","time":"DNF","points":"0"},{"position":"NC","number":"20","racerFirstName":"Chico","racerLastName":"Serra","racerShortName":"SER","car":"Fittipaldi Ford","laps":"18","time":"DNF","points":"0"},{"position":"NC","number":"35","racerFirstName":"Derek","racerLastName":"Warwick","racerShortName":"WAR","car":"Toleman Hart","laps":"15","time":"DNF","points":"0"},{"position":"NC","number":"26","racerFirstName":"Jacques","racerLastName":"Laffite","racerShortName":"LAF","car":"Ligier Matra","laps":"4","time":"DNF","points":"0"}]},{"raceId":"448/germany","grandPrix":"Germany","result":[{"position":"1","number":"27","racerFirstName":"Patrick","racerLastName":"Tambay","racerShortName":"TAM","car":"Ferrari","laps":"45","time":"1:27:25.178","points":"9"},{"position":"2","number":"16","racerFirstName":"Rene","racerLastName":"Arnoux","racerShortName":"ARN","car":"Renault","laps":"45","time":"+16.380s","points":"6"},{"position":"3","number":"6","racerFirstName":"Keke","racerLastName":"Rosberg","racerShortName":"ROS","car":"Williams Ford","laps":"44","time":"+1 lap","points":"4"},{"position":"4","number":"3","racerFirstName":"Michele","racerLastName":"Alboreto","racerShortName":"ALB","car":"Tyrrell Ford","laps":"44","time":"+1 lap","points":"3"},{"position":"5","number":"23","racerFirstName":"Bruno","racerLastName":"Giacomelli","racerShortName":"GIA","car":"Alfa Romeo","laps":"44","time":"+1 lap","points":"2"},{"position":"6","number":"29","racerFirstName":"Marc","racerLastName":"Surer","racerShortName":"SUR","car":"Arrows Ford","laps":"44","time":"+1 lap","points":"1"},{"position":"7","number":"4","racerFirstName":"Brian","racerLastName":"Henton","racerShortName":"HEN","car":"Tyrrell Ford","laps":"44","time":"+1 lap","points":"0"},{"position":"8","number":"14","racerFirstName":"Roberto","racerLastName":"Guerrero","racerShortName":"GUE","car":"Ensign Ford","laps":"44","time":"+1 lap","points":"0"},{"position":"9","number":"12","racerFirstName":"Nigel","racerLastName":"Mansell","racerShortName":"MAN","car":"Lotus Ford","laps":"43","time":"+2 laps","points":"0"},{"position":"10","number":"35","racerFirstName":"Derek","racerLastName":"Warwick","racerShortName":"WAR","car":"Toleman Hart","laps":"43","time":"+2 laps","points":"0"},{"position":"11","number":"20","racerFirstName":"Chico","racerLastName":"Serra","racerShortName":"SER","car":"Fittipaldi Ford","laps":"43","time":"+2 laps","points":"0"},{"position":"NC","number":"7","racerFirstName":"John","racerLastName":"Watson","racerShortName":"WAT","car":"McLaren Ford","laps":"36","time":"DNF","points":"0"},{"position":"NC","number":"26","racerFirstName":"Jacques","racerLastName":"Laffite","racerShortName":"LAF","car":"Ligier Matra","laps":"36","time":"DNF","points":"0"},{"position":"NC","number":"5","racerFirstName":"Derek","racerLastName":"Daly","racerShortName":"DAL","car":"Williams Ford","laps":"25","time":"DNF","points":"0"},{"position":"NC","number":"18","racerFirstName":"Raul","racerLastName":"Boesel","racerShortName":"BOE","car":"March Ford","laps":"22","time":"DNF","points":"0"},{"position":"NC","number":"11","racerFirstName":"Elio","racerLastName":"de Angelis","racerShortName":"DEA","car":"Lotus Ford","laps":"21","time":"DNF","points":"0"},{"position":"NC","number":"1","racerFirstName":"Nelson","racerLastName":"Piquet","racerShortName":"PIQ","car":"Brabham BMW","laps":"18","time":"DNF","points":"0"},{"position":"NC","number":"10","racerFirstName":"Eliseo","racerLastName":"Salazar","racerShortName":"SAL","car":"ATS Ford","laps":"17","time":"DNF","points":"0"},{"position":"NC","number":"15","racerFirstName":"Alain","racerLastName":"Prost","racerShortName":"PRO","car":"Renault","laps":"14","time":"DNF","points":"0"},{"position":"NC","number":"2","racerFirstName":"Riccardo","racerLastName":"Patrese","racerShortName":"PAT","car":"Brabham BMW","laps":"13","time":"DNF","points":"0"},{"position":"NC","number":"22","racerFirstName":"Andrea","racerLastName":"de Cesaris","racerShortName":"DEC","car":"Alfa Romeo","laps":"9","time":"DNF","points":"0"},{"position":"NC","number":"25","racerFirstName":"Eddie","racerLastName":"Cheever","racerShortName":"CHE","car":"Ligier Matra","laps":"8","time":"DNF","points":"0"},{"position":"NC","number":"30","racerFirstName":"Mauro","racerLastName":"Baldi","racerShortName":"BAL","car":"Arrows Ford","laps":"6","time":"DNF","points":"0"},{"position":"NC","number":"31","racerFirstName":"Jean-Pierre","racerLastName":"Jarier","racerShortName":"JAR","car":"Osella Ford","laps":"3","time":"DNF","points":"0"},{"position":"NC","number":"9","racerFirstName":"Manfred","racerLastName":"Winkelhock","racerShortName":"WIN","car":"ATS Ford","laps":"3","time":"DNF","points":"0"}]},{"raceId":"450/switzerland","grandPrix":"France","result":[{"position":"1","number":"6","racerFirstName":"Keke","racerLastName":"Rosberg","racerShortName":"ROS","car":"Williams Ford","laps":"80","time":"1:32:41.087","points":"9"},{"position":"2","number":"15","racerFirstName":"Alain","racerLastName":"Prost","racerShortName":"PRO","car":"Renault","laps":"80","time":"+4.440s","points":"6"},{"position":"3","number":"8","racerFirstName":"Niki","racerLastName":"Lauda","racerShortName":"LAU","car":"McLaren Ford","laps":"80","time":"+60.340s","points":"4"},{"position":"4","number":"1","racerFirstName":"Nelson","racerLastName":"Piquet","racerShortName":"PIQ","car":"Brabham BMW","laps":"79","time":"+1 lap","points":"3"},{"position":"5","number":"2","racerFirstName":"Riccardo","racerLastName":"Patrese","racerShortName":"PAT","car":"Brabham BMW","laps":"79","time":"+1 lap","points":"2"},{"position":"6","number":"11","racerFirstName":"Elio","racerLastName":"de Angelis","racerShortName":"DEA","car":"Lotus Ford","laps":"79","time":"+1 lap","points":"1"},{"position":"7","number":"3","racerFirstName":"Michele","racerLastName":"Alboreto","racerShortName":"ALB","car":"Tyrrell Ford","laps":"79","time":"+1 lap","points":"0"},{"position":"8","number":"12","racerFirstName":"Nigel","racerLastName":"Mansell","racerShortName":"MAN","car":"Lotus Ford","laps":"79","time":"+1 lap","points":"0"},{"position":"9","number":"5","racerFirstName":"Derek","racerLastName":"Daly","racerShortName":"DAL","car":"Williams Ford","laps":"79","time":"+1 lap","points":"0"},{"position":"10","number":"22","racerFirstName":"Andrea","racerLastName":"de Cesaris","racerShortName":"DEC","car":"Alfa Romeo","laps":"78","time":"+2 laps","points":"0"},{"position":"11","number":"4","racerFirstName":"Brian","racerLastName":"Henton","racerShortName":"HEN","car":"Tyrrell Ford","laps":"78","time":"+2 laps","points":"0"},{"position":"12","number":"23","racerFirstName":"Bruno","racerLastName":"Giacomelli","racerShortName":"GIA","car":"Alfa Romeo","laps":"78","time":"+2 laps","points":"0"},{"position":"13","number":"7","racerFirstName":"John","racerLastName":"Watson","racerShortName":"WAT","car":"McLaren Ford","laps":"77","time":"+3 laps","points":"0"},{"position":"14","number":"10","racerFirstName":"Eliseo","racerLastName":"Salazar","racerShortName":"SAL","car":"ATS Ford","laps":"77","time":"+3 laps","points":"0"},{"position":"15","number":"29","racerFirstName":"Marc","racerLastName":"Surer","racerShortName":"SUR","car":"Arrows Ford","laps":"76","time":"+4 laps","points":"0"},{"position":"16","number":"16","racerFirstName":"Rene","racerLastName":"Arnoux","racerShortName":"ARN","car":"Renault","laps":"75","time":"DNF","points":"0"},{"position":"NC","number":"25","racerFirstName":"Eddie","racerLastName":"Cheever","racerShortName":"CHE","car":"Ligier Matra","laps":"70","time":"DNC","points":"0"},{"position":"NC","number":"9","racerFirstName":"Manfred","racerLastName":"Winkelhock","racerShortName":"WIN","car":"ATS Ford","laps":"55","time":"DNF","points":"0"},{"position":"NC","number":"31","racerFirstName":"Jean-Pierre","racerLastName":"Jarier","racerShortName":"JAR","car":"Osella Ford","laps":"44","time":"DNF","points":"0"},{"position":"NC","number":"26","racerFirstName":"Jacques","racerLastName":"Laffite","racerShortName":"LAF","car":"Ligier Matra","laps":"33","time":"DNF","points":"0"},{"position":"NC","number":"36","racerFirstName":"Teo","racerLastName":"Fabi","racerShortName":"FAB","car":"Toleman Hart","laps":"31","time":"DNF","points":"0"},{"position":"NC","number":"18","racerFirstName":"Raul","racerLastName":"Boesel","racerShortName":"BOE","car":"March Ford","laps":"31","time":"DNF","points":"0"},{"position":"NC","number":"17","racerFirstName":"Rupert","racerLastName":"Keegan","racerShortName":"KEE","car":"March Ford","laps":"25","time":"DNF","points":"0"},{"position":"NC","number":"35","racerFirstName":"Derek","racerLastName":"Warwick","racerShortName":"WAR","car":"Toleman Hart","laps":"24","time":"DNF","points":"0"},{"position":"NC","number":"14","racerFirstName":"Roberto","racerLastName":"Guerrero","racerShortName":"GUE","car":"Ensign Ford","laps":"4","time":"DNF","points":"0"}]},{"raceId":"451/italy","grandPrix":"Italy","result":[{"position":"1","number":"16","racerFirstName":"Rene","racerLastName":"Arnoux","racerShortName":"ARN","car":"Renault","laps":"52","time":"1:22:25.734","points":"9"},{"position":"2","number":"27","racerFirstName":"Patrick","racerLastName":"Tambay","racerShortName":"TAM","car":"Ferrari","laps":"52","time":"+14.060s","points":"6"},{"position":"3","number":"28","racerFirstName":"Mario","racerLastName":"Andretti","racerShortName":"AND","car":"Ferrari","laps":"52","time":"+48.450s","points":"4"},{"position":"4","number":"7","racerFirstName":"John","racerLastName":"Watson","racerShortName":"WAT","car":"McLaren Ford","laps":"52","time":"+87.850s","points":"3"},{"position":"5","number":"3","racerFirstName":"Michele","racerLastName":"Alboreto","racerShortName":"ALB","car":"Tyrrell Ford","laps":"51","time":"+1 lap","points":"2"},{"position":"6","number":"25","racerFirstName":"Eddie","racerLastName":"Cheever","racerShortName":"CHE","car":"Ligier Matra","laps":"51","time":"+1 lap","points":"1"},{"position":"7","number":"12","racerFirstName":"Nigel","racerLastName":"Mansell","racerShortName":"MAN","car":"Lotus Ford","laps":"51","time":"+1 lap","points":"0"},{"position":"8","number":"6","racerFirstName":"Keke","racerLastName":"Rosberg","racerShortName":"ROS","car":"Williams Ford","laps":"50","time":"+2 laps","points":"0"},{"position":"9","number":"10","racerFirstName":"Eliseo","racerLastName":"Salazar","racerShortName":"SAL","car":"ATS Ford","laps":"50","time":"+2 laps","points":"0"},{"position":"10","number":"22","racerFirstName":"Andrea","racerLastName":"de Cesaris","racerShortName":"DEC","car":"Alfa Romeo","laps":"50","time":"+2 laps","points":"0"},{"position":"11","number":"20","racerFirstName":"Chico","racerLastName":"Serra","racerShortName":"SER","car":"Fittipaldi Ford","laps":"49","time":"+3 laps","points":"0"},{"position":"12","number":"30","racerFirstName":"Mauro","racerLastName":"Baldi","racerShortName":"BAL","car":"Arrows Ford","laps":"49","time":"+3 laps","points":"0"},{"position":"NC","number":"14","racerFirstName":"Roberto","racerLastName":"Guerrero","racerShortName":"GUE","car":"Ensign Ford","laps":"40","time":"+12 laps","points":"0"},{"position":"NC","number":"11","racerFirstName":"Elio","racerLastName":"de Angelis","racerShortName":"DEA","car":"Lotus Ford","laps":"34","time":"DNF","points":"0"},{"position":"NC","number":"23","racerFirstName":"Bruno","racerLastName":"Giacomelli","racerShortName":"GIA","car":"Alfa Romeo","laps":"32","time":"DNF","points":"0"},{"position":"NC","number":"29","racerFirstName":"Marc","racerLastName":"Surer","racerShortName":"SUR","car":"Arrows Ford","laps":"28","time":"DNF","points":"0"},{"position":"NC","number":"15","racerFirstName":"Alain","racerLastName":"Prost","racerShortName":"PRO","car":"Renault","laps":"27","time":"DNF","points":"0"},{"position":"NC","number":"8","racerFirstName":"Niki","racerLastName":"Lauda","racerShortName":"LAU","car":"McLaren Ford","laps":"22","time":"DNF","points":"0"},{"position":"NC","number":"31","racerFirstName":"Jean-Pierre","racerLastName":"Jarier","racerShortName":"JAR","car":"Osella Ford","laps":"10","time":"DNF","points":"0"},{"position":"NC","number":"1","racerFirstName":"Nelson","racerLastName":"Piquet","racerShortName":"PIQ","car":"Brabham BMW","laps":"7","time":"DNF","points":"0"},{"position":"NC","number":"2","racerFirstName":"Riccardo","racerLastName":"Patrese","racerShortName":"PAT","car":"Brabham BMW","laps":"6","time":"DNF","points":"0"},{"position":"NC","number":"26","racerFirstName":"Jacques","racerLastName":"Laffite","racerShortName":"LAF","car":"Ligier Matra","laps":"5","time":"DNF","points":"0"},{"position":"NC","number":"36","racerFirstName":"Teo","racerLastName":"Fabi","racerShortName":"FAB","car":"Toleman Hart","laps":"2","time":"DNF","points":"0"},{"position":"NC","number":"5","racerFirstName":"Derek","racerLastName":"Daly","racerShortName":"DAL","car":"Williams Ford","laps":"0","time":"DNF","points":"0"},{"position":"NC","number":"35","racerFirstName":"Derek","racerLastName":"Warwick","racerShortName":"WAR","car":"Toleman Hart","laps":"0","time":"DNF","points":"0"},{"position":"NC","number":"4","racerFirstName":"Brian","racerLastName":"Henton","racerShortName":"HEN","car":"Tyrrell Ford","laps":"0","time":"DNF","points":"0"}]},{"raceId":"449/austria","grandPrix":"Austria","result":[{"position":"1","number":"11","racerFirstName":"Elio","racerLastName":"de Angelis","racerShortName":"DEA","car":"Lotus Ford","laps":"53","time":"1:25:02.212","points":"9"},{"position":"2","number":"6","racerFirstName":"Keke","racerLastName":"Rosberg","racerShortName":"ROS","car":"Williams Ford","laps":"53","time":"+0.050s","points":"6"},{"position":"3","number":"26","racerFirstName":"Jacques","racerLastName":"Laffite","racerShortName":"LAF","car":"Ligier Matra","laps":"52","time":"+1 lap","points":"4"},{"position":"4","number":"27","racerFirstName":"Patrick","racerLastName":"Tambay","racerShortName":"TAM","car":"Ferrari","laps":"52","time":"+1 lap","points":"3"},{"position":"5","number":"8","racerFirstName":"Niki","racerLastName":"Lauda","racerShortName":"LAU","car":"McLaren Ford","laps":"52","time":"+1 lap","points":"2"},{"position":"6","number":"30","racerFirstName":"Mauro","racerLastName":"Baldi","racerShortName":"BAL","car":"Arrows Ford","laps":"52","time":"+1 lap","points":"1"},{"position":"7","number":"20","racerFirstName":"Chico","racerLastName":"Serra","racerShortName":"SER","car":"Fittipaldi Ford","laps":"51","time":"+2 laps","points":"0"},{"position":"8","number":"15","racerFirstName":"Alain","racerLastName":"Prost","racerShortName":"PRO","car":"Renault","laps":"48","time":"DNF","points":"0"},{"position":"NC","number":"7","racerFirstName":"John","racerLastName":"Watson","racerShortName":"WAT","car":"McLaren Ford","laps":"44","time":"DNF","points":"0"},{"position":"NC","number":"4","racerFirstName":"Brian","racerLastName":"Henton","racerShortName":"HEN","car":"Tyrrell Ford","laps":"32","time":"DNF","points":"0"},{"position":"NC","number":"1","racerFirstName":"Nelson","racerLastName":"Piquet","racerShortName":"PIQ","car":"Brabham BMW","laps":"31","time":"DNF","points":"0"},{"position":"NC","number":"33","racerFirstName":"Tommy","racerLastName":"Byrne","racerShortName":"BYR","car":"Theodore Ford","laps":"28","time":"DNF","points":"0"},{"position":"NC","number":"29","racerFirstName":"Marc","racerLastName":"Surer","racerShortName":"SUR","car":"Arrows Ford","laps":"28","time":"DNF","points":"0"},{"position":"NC","number":"2","racerFirstName":"Riccardo","racerLastName":"Patrese","racerShortName":"PAT","car":"Brabham BMW","laps":"27","time":"DNF","points":"0"},{"position":"NC","number":"25","racerFirstName":"Eddie","racerLastName":"Cheever","racerShortName":"CHE","car":"Ligier Matra","laps":"22","time":"DNF","points":"0"},{"position":"NC","number":"12","racerFirstName":"Nigel","racerLastName":"Mansell","racerShortName":"MAN","car":"Lotus Ford","laps":"17","time":"DNF","points":"0"},{"position":"NC","number":"16","racerFirstName":"Rene","racerLastName":"Arnoux","racerShortName":"ARN","car":"Renault","laps":"16","time":"DNF","points":"0"},{"position":"NC","number":"9","racerFirstName":"Manfred","racerLastName":"Winkelhock","racerShortName":"WIN","car":"ATS Ford","laps":"15","time":"DNF","points":"0"},{"position":"NC","number":"35","racerFirstName":"Derek","racerLastName":"Warwick","racerShortName":"WAR","car":"Toleman Hart","laps":"7","time":"DNF","points":"0"},{"position":"NC","number":"36","racerFirstName":"Teo","racerLastName":"Fabi","racerShortName":"FAB","car":"Toleman Hart","laps":"7","time":"DNF","points":"0"},{"position":"NC","number":"14","racerFirstName":"Roberto","racerLastName":"Guerrero","racerShortName":"GUE","car":"Ensign Ford","laps":"6","time":"DNF","points":"0"},{"position":"NC","number":"3","racerFirstName":"Michele","racerLastName":"Alboreto","racerShortName":"ALB","car":"Tyrrell Ford","laps":"1","time":"DNF","points":"0"},{"position":"NC","number":"17","racerFirstName":"Rupert","racerLastName":"Keegan","racerShortName":"KEE","car":"March Ford","laps":"1","time":"DNF","points":"0"},{"position":"NC","number":"22","racerFirstName":"Andrea","racerLastName":"de Cesaris","racerShortName":"DEC","car":"Alfa Romeo","laps":"0","time":"DNF","points":"0"},{"position":"NC","number":"5","racerFirstName":"Derek","racerLastName":"Daly","racerShortName":"DAL","car":"Williams Ford","laps":"0","time":"DNF","points":"0"},{"position":"NC","number":"23","racerFirstName":"Bruno","racerLastName":"Giacomelli","racerShortName":"GIA","car":"Alfa Romeo","laps":"0","time":"DNF","points":"0"}]},{"raceId":"444/canada","grandPrix":"Canada","result":[{"position":"1","number":"1","racerFirstName":"Nelson","racerLastName":"Piquet","racerShortName":"PIQ","car":"Brabham BMW","laps":"70","time":"1:46:39.577","points":"9"},{"position":"2","number":"2","racerFirstName":"Riccardo","racerLastName":"Patrese","racerShortName":"PAT","car":"Brabham Ford","laps":"70","time":"+13.800s","points":"6"},{"position":"3","number":"7","racerFirstName":"John","racerLastName":"Watson","racerShortName":"WAT","car":"McLaren Ford","laps":"70","time":"+61.840s","points":"4"},{"position":"4","number":"11","racerFirstName":"Elio","racerLastName":"de Angelis","racerShortName":"DEA","car":"Lotus Ford","laps":"69","time":"+1 lap","points":"3"},{"position":"5","number":"29","racerFirstName":"Marc","racerLastName":"Surer","racerShortName":"SUR","car":"Arrows Ford","laps":"69","time":"+1 lap","points":"2"},{"position":"6","number":"22","racerFirstName":"Andrea","racerLastName":"de Cesaris","racerShortName":"DEC","car":"Alfa Romeo","laps":"68","time":"DNF","points":"1"},{"position":"7","number":"5","racerFirstName":"Derek","racerLastName":"Daly","racerShortName":"DAL","car":"Williams Ford","laps":"68","time":"DNF","points":"0"},{"position":"8","number":"30","racerFirstName":"Mauro","racerLastName":"Baldi","racerShortName":"BAL","car":"Arrows Ford","laps":"68","time":"+2 laps","points":"0"},{"position":"9","number":"28","racerFirstName":"Didier","racerLastName":"Pironi","racerShortName":"PIR","car":"Ferrari","laps":"67","time":"+3 laps","points":"0"},{"position":"10","number":"25","racerFirstName":"Eddie","racerLastName":"Cheever","racerShortName":"CHE","car":"Ligier Matra","laps":"66","time":"DNF","points":"0"},{"position":"11","number":"17","racerFirstName":"Jochen","racerLastName":"Mass","racerShortName":"MAS","car":"March Ford","laps":"66","time":"+4 laps","points":"0"},{"position":"NC","number":"4","racerFirstName":"Brian","racerLastName":"Henton","racerShortName":"HEN","car":"Tyrrell Ford","laps":"59","time":"+11 laps","points":"0"},{"position":"NC","number":"6","racerFirstName":"Keke","racerLastName":"Rosberg","racerShortName":"ROS","car":"Williams Ford","laps":"52","time":"DNF","points":"0"},{"position":"NC","number":"18","racerFirstName":"Raul","racerLastName":"Boesel","racerShortName":"BOE","car":"March Ford","laps":"47","time":"DNF","points":"0"},{"position":"NC","number":"3","racerFirstName":"Michele","racerLastName":"Alboreto","racerShortName":"ALB","car":"Tyrrell Ford","laps":"41","time":"DNF","points":"0"},{"position":"NC","number":"15","racerFirstName":"Alain","racerLastName":"Prost","racerShortName":"PRO","car":"Renault","laps":"30","time":"DNF","points":"0"},{"position":"NC","number":"16","racerFirstName":"Rene","racerLastName":"Arnoux","racerShortName":"ARN","car":"Renault","laps":"28","time":"DNF","points":"0"},{"position":"NC","number":"10","racerFirstName":"Eliseo","racerLastName":"Salazar","racerShortName":"SAL","car":"ATS Ford","laps":"20","time":"DNF","points":"0"},{"position":"NC","number":"8","racerFirstName":"Niki","racerLastName":"Lauda","racerShortName":"LAU","car":"McLaren Ford","laps":"17","time":"DNF","points":"0"},{"position":"NC","number":"26","racerFirstName":"Jacques","racerLastName":"Laffite","racerShortName":"LAF","car":"Ligier Matra","laps":"8","time":"DNF","points":"0"},{"position":"NC","number":"14","racerFirstName":"Roberto","racerLastName":"Guerrero","racerShortName":"GUE","car":"Ensign Ford","laps":"2","time":"DNF","points":"0"},{"position":"NC","number":"23","racerFirstName":"Bruno","racerLastName":"Giacomelli","racerShortName":"GIA","car":"Alfa Romeo","laps":"1","time":"DNF","points":"0"},{"position":"NC","number":"12","racerFirstName":"Nigel","racerLastName":"Mansell","racerShortName":"MAN","car":"Lotus Ford","laps":"1","time":"DNF","points":"0"},{"position":"NC","number":"33","racerFirstName":"Geoff","racerLastName":"Lees","racerShortName":"LEE","car":"Theodore Ford","laps":"0","time":"DNF","points":"0"},{"position":"NC","number":"31","racerFirstName":"Jean-Pierre","racerLastName":"Jarier","racerShortName":"JAR","car":"Osella Ford","laps":"0","time":"DNF","points":"0"},{"position":"NC","number":"32","racerFirstName":"Riccardo","racerLastName":"Paletti","racerShortName":"PAL","car":"Osella Ford","laps":"0","time":"DNF","points":"0"}]},{"raceId":"447/france","grandPrix":"France","result":[{"position":"1","number":"16","racerFirstName":"Rene","racerLastName":"Arnoux","racerShortName":"ARN","car":"Renault","laps":"54","time":"1:33:33.217","points":"9"},{"position":"2","number":"15","racerFirstName":"Alain","racerLastName":"Prost","racerShortName":"PRO","car":"Renault","laps":"54","time":"+17.310s","points":"6"},{"position":"3","number":"28","racerFirstName":"Didier","racerLastName":"Pironi","racerShortName":"PIR","car":"Ferrari","laps":"54","time":"+42.130s","points":"4"},{"position":"4","number":"27","racerFirstName":"Patrick","racerLastName":"Tambay","racerShortName":"TAM","car":"Ferrari","laps":"54","time":"+76.240s","points":"3"},{"position":"5","number":"6","racerFirstName":"Keke","racerLastName":"Rosberg","racerShortName":"ROS","car":"Williams Ford","laps":"54","time":"+90.990s","points":"2"},{"position":"6","number":"3","racerFirstName":"Michele","racerLastName":"Alboreto","racerShortName":"ALB","car":"Tyrrell Ford","laps":"54","time":"+92.340s","points":"1"},{"position":"7","number":"5","racerFirstName":"Derek","racerLastName":"Daly","racerShortName":"DAL","car":"Williams Ford","laps":"53","time":"+1 lap","points":"0"},{"position":"8","number":"8","racerFirstName":"Niki","racerLastName":"Lauda","racerShortName":"LAU","car":"McLaren Ford","laps":"53","time":"+1 lap","points":"0"},{"position":"9","number":"23","racerFirstName":"Bruno","racerLastName":"Giacomelli","racerShortName":"GIA","car":"Alfa Romeo","laps":"53","time":"+1 lap","points":"0"},{"position":"10","number":"4","racerFirstName":"Brian","racerLastName":"Henton","racerShortName":"HEN","car":"Tyrrell Ford","laps":"53","time":"+1 lap","points":"0"},{"position":"11","number":"9","racerFirstName":"Manfred","racerLastName":"Winkelhock","racerShortName":"WIN","car":"ATS Ford","laps":"52","time":"+2 laps","points":"0"},{"position":"12","number":"12","racerFirstName":"Geoff","racerLastName":"Lees","racerShortName":"LEE","car":"Lotus Ford","laps":"52","time":"+2 laps","points":"0"},{"position":"13","number":"29","racerFirstName":"Marc","racerLastName":"Surer","racerShortName":"SUR","car":"Arrows Ford","laps":"52","time":"+2 laps","points":"0"},{"position":"14","number":"26","racerFirstName":"Jacques","racerLastName":"Laffite","racerShortName":"LAF","car":"Ligier Matra","laps":"51","time":"+3 laps","points":"0"},{"position":"15","number":"35","racerFirstName":"Derek","racerLastName":"Warwick","racerShortName":"WAR","car":"Toleman Hart","laps":"50","time":"+4 laps","points":"0"},{"position":"16","number":"25","racerFirstName":"Eddie","racerLastName":"Cheever","racerShortName":"CHE","car":"Ligier Matra","laps":"49","time":"+5 laps","points":"0"},{"position":"NC","number":"22","racerFirstName":"Andrea","racerLastName":"de Cesaris","racerShortName":"DEC","car":"Alfa Romeo","laps":"25","time":"DNF","points":"0"},{"position":"NC","number":"1","racerFirstName":"Nelson","racerLastName":"Piquet","racerShortName":"PIQ","car":"Brabham BMW","laps":"23","time":"DNF","points":"0"},{"position":"NC","number":"11","racerFirstName":"Elio","racerLastName":"de Angelis","racerShortName":"DEA","car":"Lotus Ford","laps":"17","time":"DNF","points":"0"},{"position":"NC","number":"7","racerFirstName":"John","racerLastName":"Watson","racerShortName":"WAT","car":"McLaren Ford","laps":"13","time":"DNF","points":"0"},{"position":"NC","number":"17","racerFirstName":"Jochen","racerLastName":"Mass","racerShortName":"MAS","car":"March Ford","laps":"10","time":"DNF","points":"0"},{"position":"NC","number":"30","racerFirstName":"Mauro","racerLastName":"Baldi","racerShortName":"BAL","car":"Arrows Ford","laps":"10","time":"DNF","points":"0"},{"position":"NC","number":"2","racerFirstName":"Riccardo","racerLastName":"Patrese","racerShortName":"PAT","car":"Brabham BMW","laps":"8","time":"DNF","points":"0"},{"position":"NC","number":"10","racerFirstName":"Eliseo","racerLastName":"Salazar","racerShortName":"SAL","car":"ATS Ford","laps":"2","time":"DNF","points":"0"},{"position":"NC","number":"36","racerFirstName":"Teo","racerLastName":"Fabi","racerShortName":"FAB","car":"Toleman Hart","laps":"0","time":"DNF","points":"0"},{"position":"NC","number":"31","racerFirstName":"Jean-Pierre","racerLastName":"Jarier","racerShortName":"JAR","car":"Osella Ford","laps":"0","time":"DNF","points":"0"}]},{"raceId":"438/brazil","grandPrix":"Brazil","result":[{"position":"DQ","number":"1","racerFirstName":"Nelson","racerLastName":"Piquet","racerShortName":"PIQ","car":"Brabham Ford","laps":"63","time":"DSQ","points":"0"},{"position":"DQ","number":"6","racerFirstName":"Keke","racerLastName":"Rosberg","racerShortName":"ROS","car":"Williams Ford","laps":"63","time":"DSQ","points":"0"},{"position":"1","number":"15","racerFirstName":"Alain","racerLastName":"Prost","racerShortName":"PRO","car":"Renault","laps":"63","time":"1:44:33.134","points":"9"},{"position":"2","number":"7","racerFirstName":"John","racerLastName":"Watson","racerShortName":"WAT","car":"McLaren Ford","laps":"63","time":"+2.990s","points":"6"},{"position":"3","number":"12","racerFirstName":"Nigel","racerLastName":"Mansell","racerShortName":"MAN","car":"Lotus Ford","laps":"63","time":"+36.860s","points":"4"},{"position":"4","number":"3","racerFirstName":"Michele","racerLastName":"Alboreto","racerShortName":"ALB","car":"Tyrrell Ford","laps":"63","time":"+50.760s","points":"3"},{"position":"5","number":"9","racerFirstName":"Manfred","racerLastName":"Winkelhock","racerShortName":"WIN","car":"ATS Ford","laps":"62","time":"+1 lap","points":"2"},{"position":"6","number":"28","racerFirstName":"Didier","racerLastName":"Pironi","racerShortName":"PIR","car":"Ferrari","laps":"62","time":"+1 lap","points":"1"},{"position":"7","number":"4","racerFirstName":"Slim","racerLastName":"Borgudd","racerShortName":"BOR","car":"Tyrrell Ford","laps":"61","time":"+2 laps","points":"0"},{"position":"8","number":"17","racerFirstName":"Jochen","racerLastName":"Mass","racerShortName":"MAS","car":"March Ford","laps":"61","time":"+2 laps","points":"0"},{"position":"9","number":"31","racerFirstName":"Jean-Pierre","racerLastName":"Jarier","racerShortName":"JAR","car":"Osella Ford","laps":"60","time":"+3 laps","points":"0"},{"position":"10","number":"30","racerFirstName":"Mauro","racerLastName":"Baldi","racerShortName":"BAL","car":"Arrows Ford","laps":"57","time":"+6 laps","points":"0"},{"position":"NC","number":"10","racerFirstName":"Eliseo","racerLastName":"Salazar","racerShortName":"SAL","car":"ATS Ford","laps":"38","time":"DNF","points":"0"},{"position":"NC","number":"20","racerFirstName":"Chico","racerLastName":"Serra","racerShortName":"SER","car":"Fittipaldi Ford","laps":"36","time":"DNF","points":"0"},{"position":"NC","number":"2","racerFirstName":"Riccardo","racerLastName":"Patrese","racerShortName":"PAT","car":"Brabham Ford","laps":"34","time":"DNF","points":"0"},{"position":"NC","number":"27","racerFirstName":"Gilles","racerLastName":"Villeneuve","racerShortName":"VIL","car":"Ferrari","laps":"29","time":"DNF","points":"0"},{"position":"NC","number":"8","racerFirstName":"Niki","racerLastName":"Lauda","racerShortName":"LAU","car":"McLaren Ford","laps":"22","time":"DNF","points":"0"},{"position":"NC","number":"16","racerFirstName":"Rene","racerLastName":"Arnoux","racerShortName":"ARN","car":"Renault","laps":"21","time":"DNF","points":"0"},{"position":"NC","number":"5","racerFirstName":"Carlos","racerLastName":"Reutemann","racerShortName":"REU","car":"Williams Ford","laps":"21","time":"DNF","points":"0"},{"position":"NC","number":"11","racerFirstName":"Elio","racerLastName":"de Angelis","racerShortName":"DEA","car":"Lotus Ford","laps":"21","time":"DNF","points":"0"},{"position":"NC","number":"25","racerFirstName":"Eddie","racerLastName":"Cheever","racerShortName":"CHE","car":"Ligier Matra","laps":"19","time":"DNF","points":"0"},{"position":"NC","number":"23","racerFirstName":"Bruno","racerLastName":"Giacomelli","racerShortName":"GIA","car":"Alfa Romeo","laps":"16","time":"DNF","points":"0"},{"position":"NC","number":"26","racerFirstName":"Jacques","racerLastName":"Laffite","racerShortName":"LAF","car":"Ligier Matra","laps":"15","time":"DNF","points":"0"},{"position":"NC","number":"22","racerFirstName":"Andrea","racerLastName":"de Cesaris","racerShortName":"DEC","car":"Alfa Romeo","laps":"14","time":"DNF","points":"0"},{"position":"NC","number":"33","racerFirstName":"Derek","racerLastName":"Daly","racerShortName":"DAL","car":"Theodore Ford","laps":"12","time":"DNF","points":"0"},{"position":"NC","number":"18","racerFirstName":"Raul","racerLastName":"Boesel","racerShortName":"BOE","car":"March Ford","laps":"11","time":"DNF","points":"0"}]},{"raceId":"437/south-africa","grandPrix":"South Africa","result":[{"position":"1","number":"15","racerFirstName":"Alain","racerLastName":"Prost","racerShortName":"PRO","car":"Renault","laps":"77","time":"1:32:08.401","points":"9"},{"position":"2","number":"5","racerFirstName":"Carlos","racerLastName":"Reutemann","racerShortName":"REU","car":"Williams Ford","laps":"77","time":"+14.950s","points":"6"},{"position":"3","number":"16","racerFirstName":"Rene","racerLastName":"Arnoux","racerShortName":"ARN","car":"Renault","laps":"77","time":"+27.900s","points":"4"},{"position":"4","number":"8","racerFirstName":"Niki","racerLastName":"Lauda","racerShortName":"LAU","car":"McLaren Ford","laps":"77","time":"+32.110s","points":"3"},{"position":"5","number":"6","racerFirstName":"Keke","racerLastName":"Rosberg","racerShortName":"ROS","car":"Williams Ford","laps":"77","time":"+46.140s","points":"2"},{"position":"6","number":"7","racerFirstName":"John","racerLastName":"Watson","racerShortName":"WAT","car":"McLaren Ford","laps":"77","time":"+50.990s","points":"1"},{"position":"7","number":"3","racerFirstName":"Michele","racerLastName":"Alboreto","racerShortName":"ALB","car":"Tyrrell Ford","laps":"76","time":"+1 lap","points":"0"},{"position":"8","number":"11","racerFirstName":"Elio","racerLastName":"de Angelis","racerShortName":"DEA","car":"Lotus Ford","laps":"76","time":"+1 lap","points":"0"},{"position":"9","number":"10","racerFirstName":"Eliseo","racerLastName":"Salazar","racerShortName":"SAL","car":"ATS Ford","laps":"75","time":"+2 laps","points":"0"},{"position":"10","number":"9","racerFirstName":"Manfred","racerLastName":"Winkelhock","racerShortName":"WIN","car":"ATS Ford","laps":"75","time":"+2 laps","points":"0"},{"position":"11","number":"23","racerFirstName":"Bruno","racerLastName":"Giacomelli","racerShortName":"GIA","car":"Alfa Romeo","laps":"74","time":"+3 laps","points":"0"},{"position":"12","number":"17","racerFirstName":"Jochen","racerLastName":"Mass","racerShortName":"MAS","car":"March Ford","laps":"74","time":"+3 laps","points":"0"},{"position":"13","number":"22","racerFirstName":"Andrea","racerLastName":"de Cesaris","racerShortName":"DEC","car":"Alfa Romeo","laps":"73","time":"+4 laps","points":"0"},{"position":"14","number":"33","racerFirstName":"Derek","racerLastName":"Daly","racerShortName":"DAL","car":"Theodore Ford","laps":"73","time":"+4 laps","points":"0"},{"position":"15","number":"18","racerFirstName":"Raul","racerLastName":"Boesel","racerShortName":"BOE","car":"March Ford","laps":"72","time":"+5 laps","points":"0"},{"position":"16","number":"4","racerFirstName":"Slim","racerLastName":"Borgudd","racerShortName":"BOR","car":"Tyrrell Ford","laps":"72","time":"+5 laps","points":"0"},{"position":"17","number":"20","racerFirstName":"Chico","racerLastName":"Serra","racerShortName":"SER","car":"Fittipaldi Ford","laps":"72","time":"+5 laps","points":"0"},{"position":"18","number":"28","racerFirstName":"Didier","racerLastName":"Pironi","racerShortName":"PIR","car":"Ferrari","laps":"71","time":"+6 laps","points":"0"},{"position":"NC","number":"26","racerFirstName":"Jacques","racerLastName":"Laffite","racerShortName":"LAF","car":"Ligier Matra","laps":"54","time":"DNF","points":"0"},{"position":"NC","number":"35","racerFirstName":"Derek","racerLastName":"Warwick","racerShortName":"WAR","car":"Toleman Hart","laps":"43","time":"DNF","points":"0"},{"position":"NC","number":"2","racerFirstName":"Riccardo","racerLastName":"Patrese","racerShortName":"PAT","car":"Brabham BMW","laps":"18","time":"DNF","points":"0"},{"position":"NC","number":"25","racerFirstName":"Eddie","racerLastName":"Cheever","racerShortName":"CHE","car":"Ligier Matra","laps":"11","time":"DNF","points":"0"},{"position":"NC","number":"27","racerFirstName":"Gilles","racerLastName":"Villeneuve","racerShortName":"VIL","car":"Ferrari","laps":"6","time":"DNF","points":"0"},{"position":"NC","number":"1","racerFirstName":"Nelson","racerLastName":"Piquet","racerShortName":"PIQ","car":"Brabham BMW","laps":"3","time":"DNF","points":"0"},{"position":"NC","number":"12","racerFirstName":"Nigel","racerLastName":"Mansell","racerShortName":"MAN","car":"Lotus Ford","laps":"0","time":"DNF","points":"0"},{"position":"NC","number":"31","racerFirstName":"Jean-Pierre","racerLastName":"Jarier","racerShortName":"JAR","car":"Osella Ford","laps":"0","time":"DNF","points":"0"}]}],"allRaceResult":[{"grandPrix":"South Africa","date":"23 Jan 1982","winnerFirstName":"Alain","winnerLastName":"Prost","winnerShortName":"PRO","car":"Renault","laps":"77","time":"1:32:08.401"},{"grandPrix":"Brazil","date":"21 Mar 1982","winnerFirstName":"Alain","winnerLastName":"Prost","winnerShortName":"PRO","car":"Renault","laps":"63","time":"1:44:33.134"},{"grandPrix":"USA West","date":"04 Apr 1982","winnerFirstName":"Niki","winnerLastName":"Lauda","winnerShortName":"LAU","car":"McLaren Ford","laps":"75","time":"1:58:25.318"},{"grandPrix":"San Marino","date":"25 Apr 1982","winnerFirstName":"Didier","winnerLastName":"Pironi","winnerShortName":"PIR","car":"Ferrari","laps":"60","time":"1:36:38.887"},{"grandPrix":"Belgium","date":"09 May 1982","winnerFirstName":"John","winnerLastName":"Watson","winnerShortName":"WAT","car":"McLaren Ford","laps":"70","time":"1:35:41.995"},{"grandPrix":"Monaco","date":"23 May 1982","winnerFirstName":"Riccardo","winnerLastName":"Patrese","winnerShortName":"PAT","car":"Brabham Ford","laps":"76","time":"1:54:11.259"},{"grandPrix":"Detroit","date":"06 Jun 1982","winnerFirstName":"John","winnerLastName":"Watson","winnerShortName":"WAT","car":"McLaren Ford","laps":"62","time":"1:58:41.043"},{"grandPrix":"Canada","date":"13 Jun 1982","winnerFirstName":"Nelson","winnerLastName":"Piquet","winnerShortName":"PIQ","car":"Brabham BMW","laps":"70","time":"1:46:39.577"},{"grandPrix":"Netherlands","date":"03 Jul 1982","winnerFirstName":"Didier","winnerLastName":"Pironi","winnerShortName":"PIR","car":"Ferrari","laps":"72","time":"1:38:03.254"},{"grandPrix":"Great Britain","date":"18 Jul 1982","winnerFirstName":"Niki","winnerLastName":"Lauda","winnerShortName":"LAU","car":"McLaren Ford","laps":"76","time":"1:35:33.812"},{"grandPrix":"France","date":"25 Jul 1982","winnerFirstName":"Rene","winnerLastName":"Arnoux","winnerShortName":"ARN","car":"Renault","laps":"54","time":"1:33:33.217"},{"grandPrix":"Germany","date":"08 Aug 1982","winnerFirstName":"Patrick","winnerLastName":"Tambay","winnerShortName":"TAM","car":"Ferrari","laps":"45","time":"1:27:25.178"},{"grandPrix":"Austria","date":"15 Aug 1982","winnerFirstName":"Elio","winnerLastName":"de Angelis","winnerShortName":"DEA","car":"Lotus Ford","laps":"53","time":"1:25:02.212"},{"grandPrix":"Switzerland","date":"29 Aug 1982","winnerFirstName":"Keke","winnerLastName":"Rosberg","winnerShortName":"ROS","car":"Williams Ford","laps":"80","time":"1:32:41.087"},{"grandPrix":"Italy","date":"12 Sep 1982","winnerFirstName":"Rene","winnerLastName":"Arnoux","winnerShortName":"ARN","car":"Renault","laps":"52","time":"1:22:25.734"},{"grandPrix":"Las Vegas","date":"25 Sep 1982","winnerFirstName":"Michele","winnerLastName":"Alboreto","winnerShortName":"ALB","car":"Tyrrell Ford","laps":"75","time":"1:41:56.888"}]}